jzgutil/__init__.py
jzgutil/gangutil.py
jzgutil-1.3.0.dist-info/LICENSE
jzgutil-1.3.0.dist-info/METADATA
jzgutil-1.3.0.dist-info/WHEEL
jzgutil-1.3.0.dist-info/top_level.txt
jzgutil-1.3.0.dist-info/RECORD
