Metadata-Version: 2.1
Name: jzgutil
Version: 1.3.0
License-File: LICENSE
Requires-Dist: requests
Requires-Dist: bs4
Requires-Dist: click
